odoo10_addon_mail_template_multi_company-10.0.1.0.1.99.dev3-py3.8-nspkg.pth
odoo/addons/mail_template_multi_company/README.rst
odoo/addons/mail_template_multi_company/__init__.py
odoo/addons/mail_template_multi_company/__manifest__.py
odoo/addons/mail_template_multi_company/i18n/mail_template_multi_company.pot
odoo/addons/mail_template_multi_company/models/__init__.py
odoo/addons/mail_template_multi_company/models/mail_template.py
odoo/addons/mail_template_multi_company/readme/CONFIGURE.rst
odoo/addons/mail_template_multi_company/readme/CONTRIBUTORS.rst
odoo/addons/mail_template_multi_company/readme/DESCRIPTION.rst
odoo/addons/mail_template_multi_company/readme/USAGE.rst
odoo/addons/mail_template_multi_company/security/mail_template.xml
odoo/addons/mail_template_multi_company/static/description/icon.png
odoo/addons/mail_template_multi_company/static/description/index.html
odoo/addons/mail_template_multi_company/views/mail_template.xml
odoo10_addon_mail_template_multi_company-10.0.1.0.1.99.dev3.dist-info/METADATA
odoo10_addon_mail_template_multi_company-10.0.1.0.1.99.dev3.dist-info/WHEEL
odoo10_addon_mail_template_multi_company-10.0.1.0.1.99.dev3.dist-info/namespace_packages.txt
odoo10_addon_mail_template_multi_company-10.0.1.0.1.99.dev3.dist-info/top_level.txt
odoo10_addon_mail_template_multi_company-10.0.1.0.1.99.dev3.dist-info/RECORD
