Metadata-Version: 2.1
Name: odoo10-addon-mail-template-multi-company
Version: 10.0.1.0.1.99.dev3
Summary: Mail Template Multi Company
Home-page: https://github.com/OCA/multi-company
Author: ACSONE SA/NV,Odoo Community Association (OCA)
Author-email: support@odoo-community.org
License: AGPL-3
Platform: UNKNOWN
Classifier: Programming Language :: Python
Classifier: Framework :: Odoo
Classifier: Framework :: Odoo :: 10.0
Classifier: License :: OSI Approved :: GNU Affero General Public License v3
Classifier: Development Status :: 4 - Beta
Requires-Python: ~=2.7
Requires-Dist: odoo <10.1dev,>=10.0
